scanny/__init__.py
scanny/scanny.py
scanny-0.0.1.dist-info/LICENSE.txt
scanny-0.0.1.dist-info/METADATA
scanny-0.0.1.dist-info/WHEEL
scanny-0.0.1.dist-info/top_level.txt
scanny-0.0.1.dist-info/RECORD
