Metadata-Version: 2.1
Name: scanny
Version: 0.0.1
Summary: Module for Python. This Module will enable a user to use any flatbed scanner using python.
Home-page: https://github.com/Hardik-26/Flatbed-Scanner
Author: Hardik Shah
Author-email: hardik.2673@gmail.com
License: UNKNOWN
Platform: UNKNOWN
Classifier: Programming Language :: Python :: 3
Classifier: License :: OSI Approved :: GNU General Public License v3 (GPLv3)
Classifier: Operating System :: OS Independent
Requires-Python: >=3.6
License-File: LICENSE.txt
